kubemon/__init__.py
kubemon/__main__.py
kubemon/dataclasses.py
kubemon/decorators.py
kubemon/log.py
kubemon/pod.py
kubemon/settings.py
kubemon/cli/__init__.py
kubemon/cli/commands.py
kubemon/collector/__init__.py
kubemon/collector/collector.py
kubemon/collector/collector_client.py
kubemon/collector/commands.py
kubemon/collector/monitor_handler.py
kubemon/entities/__init__.py
kubemon/entities/base_entity.py
kubemon/entities/cpu.py
kubemon/entities/disk.py
kubemon/entities/memory.py
kubemon/entities/network.py
kubemon/exceptions/__init__.py
kubemon/exceptions/platform_exception.py
kubemon/metrics/__init__.py
kubemon/metrics/_docker.py
kubemon/metrics/cpu.py
kubemon/metrics/disk.py
kubemon/metrics/memory.py
kubemon/metrics/network.py
kubemon/monitors/__init__.py
kubemon/monitors/base.py
kubemon/monitors/daemon.py
kubemon/monitors/docker_monitor.py
kubemon/monitors/monitor.py
kubemon/monitors/process_monitor.py
kubemon/utils/__init__.py
kubemon/utils/containers.py
kubemon/utils/data.py
kubemon/utils/monitors.py
kubemon/utils/networking.py
kubemon/utils/process.py
test/__init__.py
test/utils/__init__.py
test/utils/test.py
kubemon-2.2.3.dist-info/LICENSE
kubemon-2.2.3.dist-info/METADATA
kubemon-2.2.3.dist-info/WHEEL
kubemon-2.2.3.dist-info/top_level.txt
kubemon-2.2.3.dist-info/RECORD
