Metadata-Version: 2.1
Name: kubemon
Version: 2.2.3
Summary: UNKNOWN
Home-page: https://github.com/hrchlhck/kubemon
Author: Pedro Horchulhack
Author-email: pedro.horchulhack@ppgia.pucpr.br
License: MIT
Platform: UNKNOWN
License-File: LICENSE
Requires-Dist: requests
Requires-Dist: psutil
Requires-Dist: docker
Requires-Dist: flask
Requires-Dist: flask-restful
Requires-Dist: gunicorn
